pyfleet/__init__.py
pyfleet/fleet.py
pyfleet-0.1.1.dist-info/DESCRIPTION.rst
pyfleet-0.1.1.dist-info/METADATA
pyfleet-0.1.1.dist-info/metadata.json
pyfleet-0.1.1.dist-info/RECORD
pyfleet-0.1.1.dist-info/top_level.txt
pyfleet-0.1.1.dist-info/WHEEL
