Metadata-Version: 2.0
Name: pyfleet
Version: 0.1.1
Summary: Manage CoreOS Fleets
Home-page: https://github.com/jcderr/pyfleet
Author: Jeremy Derr
Author-email: jeremy@derr.me
License: BSD
Platform: any
Classifier: Development Status :: 4 - Beta
Classifier: Intended Audience :: Developers
Classifier: Operating System :: POSIX
Classifier: Operating System :: MacOS
Classifier: Operating System :: Unix
Classifier: Programming Language :: Python
Classifier: Programming Language :: Python :: 2
Classifier: Programming Language :: Python :: 3
Classifier: Topic :: Software Development :: Libraries :: Python Modules
Requires-Dist: requests
Requires-Dist: etcd
